README.md
setup.py
graphdot/__init__.py
graphdot.egg-info/PKG-INFO
graphdot.egg-info/SOURCES.txt
graphdot.egg-info/dependency_links.txt
graphdot.egg-info/requires.txt
graphdot.egg-info/top_level.txt
graphdot/codegen/__init__.py
graphdot/codegen/cpptool.py
graphdot/codegen/sympy_printer.py
graphdot/codegen/template.py
graphdot/codegen/typetool.py
graphdot/cpp/__init__.py
graphdot/cpp/array.h
graphdot/cpp/basekernel.h
graphdot/cpp/fmath.h
graphdot/cpp/frozen_array.h
graphdot/cpp/graph.h
graphdot/cpp/marginalized_kernel.h
graphdot/cpp/metadbg.h
graphdot/cpp/numpy_type.h
graphdot/cpp/tensor_view.h
graphdot/cpp/util_cuda.h
graphdot/cpp/vecmath.h
graphdot/cpp/basekernel/convolution.h
graphdot/cpp/basekernel/dotproduct.h
graphdot/cpp/basekernel/normalize.h
graphdot/cuda/__init__.py
graphdot/cuda/array.py
graphdot/cuda/balloc.py
graphdot/cuda/resizable_array.py
graphdot/experimental/__init__.py
graphdot/experimental/metric/__init__.py
graphdot/experimental/metric/m3.py
graphdot/graph/__init__.py
graphdot/graph/_from_ase.py
graphdot/graph/_from_networkx.py
graphdot/graph/_from_pymatgen.py
graphdot/graph/_from_rdkit.py
graphdot/graph/_to_networkx.py
graphdot/graph/adjacency/__init__.py
graphdot/graph/adjacency/atomic.py
graphdot/graph/adjacency/euclidean.py
graphdot/graph/reorder/__init__.py
graphdot/graph/reorder/rcm.py
graphdot/graph/reorder/pbr/__init__.py
graphdot/graph/reorder/pbr/colnet_hypergraph.py
graphdot/graph/reorder/pbr/config.py
graphdot/graph/reorder/pbr/hypergraph.py
graphdot/graph/reorder/pbr/mnom.py
graphdot/kernel/__init__.py
graphdot/kernel/basekernel.py
graphdot/kernel/fix.py
graphdot/kernel/molecular.py
graphdot/kernel/rbf.py
graphdot/kernel/marginalized/__init__.py
graphdot/kernel/marginalized/_backend.py
graphdot/kernel/marginalized/_backend_avx.py
graphdot/kernel/marginalized/_backend_cuda.py
graphdot/kernel/marginalized/_backend_factory.py
graphdot/kernel/marginalized/_kernel.py
graphdot/kernel/marginalized/_octilegraph.py
graphdot/kernel/marginalized/_scratch.py
graphdot/kernel/marginalized/basekernel.py
graphdot/kernel/marginalized/starting_probability.py
graphdot/kernel/marginalized/template.cu
